<annotation>
	<folder>秋田犬jpg416</folder>
	<filename>akita59.jpg</filename>
	<path>C:/Users/USER/Downloads/秋田犬jpg416/akita59.jpg</path>
	<source>
		<database>Unknown</database>
	</source>
	<size>
		<width>416</width>
		<height>416</height>
		<depth>3</depth>
	</size>
	<segmented>0</segmented>
	<object>
		<name>akita</name>
		<pose>Unspecified</pose>
		<truncated>0</truncated>
		<difficult>0</difficult>
		<bndbox>
			<xmin>35</xmin>
			<ymin>131</ymin>
			<xmax>368</xmax>
			<ymax>363</ymax>
		</bndbox>
	</object>
</annotation>
