<annotation>
	<folder>臘腸jpg</folder>
	<filename>dachshund_191.jpg</filename>
	<path>C:/dogdog/臘腸jpg/dachshund_191.jpg</path>
	<source>
		<database>Unknown</database>
	</source>
	<size>
		<width>416</width>
		<height>416</height>
		<depth>3</depth>
	</size>
	<segmented>0</segmented>
	<object>
		<name>dachshund</name>
		<pose>Unspecified</pose>
		<truncated>0</truncated>
		<difficult>0</difficult>
		<bndbox>
			<xmin>53</xmin>
			<ymin>138</ymin>
			<xmax>212</xmax>
			<ymax>334</ymax>
		</bndbox>
	</object>
	<object>
		<name>dachshund</name>
		<pose>Unspecified</pose>
		<truncated>0</truncated>
		<difficult>0</difficult>
		<bndbox>
			<xmin>202</xmin>
			<ymin>36</ymin>
			<xmax>407</xmax>
			<ymax>375</ymax>
		</bndbox>
	</object>
</annotation>
